topsis/__init__.py
topsis/topsis.py
Topsis_Ojasvi_102203960-0.1.dist-info/LICENSE
Topsis_Ojasvi_102203960-0.1.dist-info/METADATA
Topsis_Ojasvi_102203960-0.1.dist-info/WHEEL
Topsis_Ojasvi_102203960-0.1.dist-info/top_level.txt
Topsis_Ojasvi_102203960-0.1.dist-info/RECORD
