Metadata-Version: 2.2
Name: Topsis-Ojasvi-102203960
Version: 0.1
Summary: A Python package for TOPSIS (Technique for Order Preference by Similarity to Ideal Solution)
Author: Ojasvi
Author-email: ojasvi@example.com
Classifier: Programming Language :: Python :: 3
Classifier: License :: OSI Approved :: MIT License
Classifier: Operating System :: OS Independent
Requires-Python: >=3.6
License-File: LICENSE
Requires-Dist: numpy
Requires-Dist: pandas
Dynamic: author
Dynamic: author-email
Dynamic: classifier
Dynamic: description-content-type
Dynamic: requires-dist
Dynamic: requires-python
Dynamic: summary
